local_llm_kit/__init__.py
local_llm_kit/chat.py
local_llm_kit/cli.py
local_llm_kit/function_calling.py
local_llm_kit/llm.py
local_llm_kit/memory.py
local_llm_kit/prompt_formatting.py
local_llm_kit/backends/__init__.py
local_llm_kit/backends/base.py
local_llm_kit/backends/llamacpp.py
local_llm_kit/backends/transformers.py
local_llm_kit-0.1.3.dist-info/licenses/LICENSE
local_llm_kit-0.1.3.dist-info/METADATA
local_llm_kit-0.1.3.dist-info/WHEEL
local_llm_kit-0.1.3.dist-info/entry_points.txt
local_llm_kit-0.1.3.dist-info/top_level.txt
local_llm_kit-0.1.3.dist-info/RECORD
