Metadata-Version: 2.4
Name: local-llm-kit
Version: 0.1.3
Summary: OpenAI-like interface for local LLMs
Author-email: Utkarsh Rajput <utkarshrajput815@gmail.com>
License-Expression: MIT
Project-URL: Homepage, https://github.com/1Utkarsh1/local-llm-kit
Project-URL: Documentation, https://local-llm-kit-package.readthedocs.io/en/latest/index.html
Project-URL: Changelog, https://github.com/1Utkarsh1/local-llm-kit/blob/main/CHANGELOG.md
Project-URL: Issues, https://github.com/1Utkarsh1/local-llm-kit/issues
Classifier: Development Status :: 3 - Alpha
Classifier: Intended Audience :: Developers
Classifier: Programming Language :: Python :: 3
Classifier: Programming Language :: Python :: 3.8
Classifier: Programming Language :: Python :: 3.9
Classifier: Programming Language :: Python :: 3.10
Classifier: Programming Language :: Python :: 3.11
Requires-Python: >=3.8
License-File: LICENSE
Requires-Dist: typing-extensions>=4.0.0
Provides-Extra: transformers
Requires-Dist: torch>=1.12.0; extra == "transformers"
Requires-Dist: transformers>=4.25.0; extra == "transformers"
Requires-Dist: accelerate>=0.16.0; extra == "transformers"
Provides-Extra: llamacpp
Requires-Dist: llama-cpp-python>=0.1.77; extra == "llamacpp"
Provides-Extra: all
Requires-Dist: torch>=1.12.0; extra == "all"
Requires-Dist: transformers>=4.25.0; extra == "all"
Requires-Dist: accelerate>=0.16.0; extra == "all"
Requires-Dist: llama-cpp-python>=0.1.77; extra == "all"
Dynamic: license-file
